gridworkbench/__init__.py
gridworkbench/containers.py
gridworkbench/devices.py
gridworkbench/workbench.py
gridworkbench/analysis/__init__.py
gridworkbench/analysis/contingencies.py
gridworkbench/analysis/packet_decomposition.py
gridworkbench/dyn/__init__.py
gridworkbench/dyn/exc_ieeet1.py
gridworkbench/dyn/gencls.py
gridworkbench/dyn/genrou.py
gridworkbench/dyn/gov_tgov1.py
gridworkbench/io/__init__.py
gridworkbench/io/default_pw_instructions.py
gridworkbench/io/grid_engine.py
gridworkbench/io/json_tool.py
gridworkbench/io/pwaux.py
gridworkbench/io/pwb_analysis.py
gridworkbench/io/pwb_dyn.py
gridworkbench/utils/__init__.py
gridworkbench/utils/exceptions.py
gridworkbench/utils/geograph.py
gridworkbench-0.0.15.dist-info/LICENSE
gridworkbench-0.0.15.dist-info/METADATA
gridworkbench-0.0.15.dist-info/WHEEL
gridworkbench-0.0.15.dist-info/top_level.txt
gridworkbench-0.0.15.dist-info/RECORD
