Metadata-Version: 2.1
Name: gridworkbench
Version: 0.0.15
Summary: Python-based data structure for electric grid models
Author: Adam Birchfield
Author-email: abirchfield@tamu.edu
Classifier: Programming Language :: Python :: 3
Classifier: License :: OSI Approved :: MIT License
Classifier: Operating System :: OS Independent
Requires-Python: >=3.6
License-File: LICENSE
Requires-Dist: esa
